sp_ask_running_total_daily_report/__init__.py
sp_ask_running_total_daily_report-0.1.6.dist-info/WHEEL
sp_ask_running_total_daily_report-0.1.6.dist-info/METADATA
sp_ask_running_total_daily_report-0.1.6.dist-info/RECORD
